kgddstools/__init__.py
kgddstools-0.2.9.0.dist-info/METADATA
kgddstools-0.2.9.0.dist-info/WHEEL
kgddstools-0.2.9.0.dist-info/top_level.txt
kgddstools-0.2.9.0.dist-info/RECORD
