Metadata-Version: 2.1
Name: kgddstools
Version: 0.2.9.0
Summary: Data science functions for convience
Home-page: https://github.com/kelvinducray/kgddstools
Author: Kelvin Ducray
Author-email: kelvin.ducray@gmail.com
License: UNKNOWN
Platform: UNKNOWN
Classifier: Programming Language :: Python :: 3
Classifier: License :: Public Domain
Classifier: Operating System :: OS Independent
